README.md
setup.cfg
setup.py
natural_selection/__init__.py
natural_selection/__version__.py
natural_selection.egg-info/PKG-INFO
natural_selection.egg-info/SOURCES.txt
natural_selection.egg-info/dependency_links.txt
natural_selection.egg-info/not-zip-safe
natural_selection.egg-info/requires.txt
natural_selection.egg-info/top_level.txt
natural_selection/genetic_algorithms/__init__.py
natural_selection/genetic_algorithms/operators/__init__.py
natural_selection/genetic_algorithms/operators/crossover.py
natural_selection/genetic_algorithms/operators/initialisation.py
natural_selection/genetic_algorithms/operators/mutation.py
natural_selection/genetic_algorithms/operators/selection/__init__.py
natural_selection/genetic_algorithms/operators/selection/parent_combination.py
natural_selection/genetic_algorithms/operators/selection/parent_selection.py
natural_selection/genetic_algorithms/operators/selection/survivor_selection.py
natural_selection/genetic_algorithms/utils/__init__.py
natural_selection/genetic_algorithms/utils/random_functions.py
natural_selection/genetic_programs/__init__.py
natural_selection/genetic_programs/node_operators/__init__.py
natural_selection/genetic_programs/operators/__init__.py
natural_selection/genetic_programs/operators/crossover.py
natural_selection/genetic_programs/operators/generate.py
natural_selection/genetic_programs/operators/initialisation.py
natural_selection/genetic_programs/operators/mutation.py
natural_selection/genetic_programs/utils/__init__.py
natural_selection/utils/__init__.py
natural_selection/utils/criteria_stopping.py
natural_selection/utils/population_growth.py
natural_selection/utils/probability_functions.py
tests/integration/__init__.py
tests/unittest/__init__.py
tests/unittest/ga/__init__.py
tests/unittest/ga/test_clone.py
tests/unittest/ga/test_crossover.py
tests/unittest/ga/test_elite_selection.py
tests/unittest/ga/test_gene.py
tests/unittest/ga/test_genome.py
tests/unittest/ga/test_individual.py
tests/unittest/ga/test_initialisation.py
tests/unittest/ga/test_island.py
tests/unittest/ga/test_multicore.py
tests/unittest/ga/test_state_engine.py
tests/unittest/gp/__init__.py
tests/unittest/gp/test_crossover_gp.py
tests/unittest/gp/test_genetic_program.py
