Metadata-Version: 2.1
Name: natural-selection
Version: 0.2.33
Summary: Tools for running evolutionary algorithm experiments
Home-page: https://github.com/Zipfian-Science/natural-selection
Author: Zipfian Science
Author-email: about@zipfian.science
License: Apache 2.0
Download-URL: https://github.com/Zipfian-Science/natural-selection/archive/v_01.tar.gz
Keywords: GENETIC ALGORITHMS,EVOLUTIONARY ALGORITHMS
Platform: UNKNOWN
Classifier: Intended Audience :: Science/Research
Classifier: Operating System :: OS Independent
Classifier: Programming Language :: Python :: 3
Classifier: Topic :: Scientific/Engineering :: Artificial Intelligence
